fife/__init__.py
fife/__main__.py
fife/base_modelers.py
fife/lgb_modelers.py
fife/nnet_survival.py
fife/pd_modelers.py
fife/processors.py
fife/tf_modelers.py
fife/utils.py
fife-1.6.2.dist-info/LICENSE.txt
fife-1.6.2.dist-info/METADATA
fife-1.6.2.dist-info/WHEEL
fife-1.6.2.dist-info/entry_points.txt
fife-1.6.2.dist-info/top_level.txt
fife-1.6.2.dist-info/RECORD
