Metadata-Version: 2.1
Name: fife
Version: 1.6.2
Summary: Finite-Interval Forecasting Engine: Machine learning models for discrete-time survival analysis and multivariate time series forecasting
Home-page: https://github.com/IDA-HumanCapital/fife
Author: Institute for Defense Analyses
Author-email: humancapital@ida.org
License: AGPLv3+
Project-URL: Bug Tracker, https://github.com/IDA-HumanCapital/fife/issues
Project-URL: Source Code, https://github.com/IDA-HumanCapital/fife
Project-URL: Documentation, https://fife.readthedocs.io/en/latest
Classifier: Development Status :: 4 - Beta
Classifier: Intended Audience :: Science/Research
Classifier: License :: OSI Approved :: GNU Affero General Public License v3 or later (AGPLv3+)
Classifier: Programming Language :: Python :: 3
Classifier: Programming Language :: Python :: 3.8
Classifier: Topic :: Scientific/Engineering :: Information Analysis
License-File: LICENSE.txt
Requires-Dist: dask[delayed]
Requires-Dist: ipython
Requires-Dist: keras
Requires-Dist: lifelines
Requires-Dist: lightgbm
Requires-Dist: matplotlib
Requires-Dist: numpy
Requires-Dist: optuna
Requires-Dist: pandas
Requires-Dist: seaborn
Requires-Dist: scikit-learn
Requires-Dist: shap
Provides-Extra: tensorflow
Requires-Dist: tensorflow ; extra == 'tensorflow'
